mathdiagram/__init__.py
mathdiagram/config.py
mathdiagram/constraints.py
mathdiagram/core.py
mathdiagram/shapes.py
mathdiagram/templates.py
mathdiagram/utils.py
mathdiagram-1.0.2.dist-info/licenses/LICENSE
mathdiagram-1.0.2.dist-info/METADATA
mathdiagram-1.0.2.dist-info/WHEEL
mathdiagram-1.0.2.dist-info/top_level.txt
mathdiagram-1.0.2.dist-info/RECORD
