Metadata-Version: 2.4
Name: mathdiagram
Version: 1.0.2
Summary: Generic mathematical diagram generation library for any topic
Home-page: https://github.com/mathdiagram/mathdiagram
Author: MathDiagram Library
Author-email: MathDiagram Library <contact@mathdiagram.com>
License: MIT
Project-URL: Homepage, https://github.com/mathdiagram/mathdiagram
Project-URL: Repository, https://github.com/mathdiagram/mathdiagram.git
Project-URL: Issues, https://github.com/mathdiagram/mathdiagram/issues
Classifier: Development Status :: 4 - Beta
Classifier: Intended Audience :: Education
Classifier: Intended Audience :: Science/Research
Classifier: License :: OSI Approved :: MIT License
Classifier: Operating System :: OS Independent
Classifier: Programming Language :: Python :: 3
Classifier: Programming Language :: Python :: 3.7
Classifier: Programming Language :: Python :: 3.8
Classifier: Programming Language :: Python :: 3.9
Classifier: Programming Language :: Python :: 3.10
Classifier: Topic :: Education
Classifier: Topic :: Scientific/Engineering :: Mathematics
Classifier: Topic :: Scientific/Engineering :: Visualization
Requires-Python: >=3.7
License-File: LICENSE
Requires-Dist: matplotlib>=3.3.0
Requires-Dist: numpy>=1.18.0
Requires-Dist: scipy>=1.5.0
Provides-Extra: dev
Requires-Dist: pytest>=6.0; extra == "dev"
Requires-Dist: black>=22.0; extra == "dev"
Requires-Dist: flake8>=4.0; extra == "dev"
Requires-Dist: mypy>=0.950; extra == "dev"
Dynamic: author
Dynamic: home-page
Dynamic: license-file
Dynamic: requires-python
